corded/__init__.py
corded/client.py
corded/constants.py
corded/errors.py
corded/helpers.py
corded/http/__init__.py
corded/http/client.py
corded/http/file.py
corded/http/ratelimiter.py
corded/http/route.py
corded/objects/__init__.py
corded/objects/base.py
corded/objects/constants.py
corded/objects/gateway.py
corded/objects/partials.py
corded/ws/__init__.py
corded/ws/client.py
corded/ws/ratelimiter.py
corded/ws/shard.py
corded-1.5.2.dist-info/LICENSE
corded-1.5.2.dist-info/WHEEL
corded-1.5.2.dist-info/METADATA
corded-1.5.2.dist-info/RECORD
